iconic/__init__.py
iconic/iconicicons.zip
iconic/jinja.py
iconic/templatetags/__init__.py
iconic/templatetags/iconic.py
iconic-1.0.0.dist-info/LICENSE
iconic-1.0.0.dist-info/METADATA
iconic-1.0.0.dist-info/WHEEL
iconic-1.0.0.dist-info/top_level.txt
iconic-1.0.0.dist-info/RECORD
