Metadata-Version: 2.1
Name: iconic
Version: 1.0.0
Summary: Use iconic.app icons in your Django and Jinja templates.
Home-page: https://github.com/monty5811/iconic
Author: Dean Montgomery
Author-email: montgomery.dean97@gmail.com
License: MIT
Project-URL: Changelog, https://github.com/monty5811/iconic/blob/main/HISTORY.rst
Project-URL: Twitter, https://twitter.com/monty5811
Keywords: Django Jinja
Platform: UNKNOWN
Classifier: Development Status :: 5 - Production/Stable
Classifier: Framework :: Django :: 2.2
Classifier: Framework :: Django :: 3.0
Classifier: Framework :: Django :: 3.1
Classifier: Framework :: Django :: 3.2
Classifier: Intended Audience :: Developers
Classifier: License :: OSI Approved :: MIT License
Classifier: Natural Language :: English
Classifier: Operating System :: OS Independent
Classifier: Programming Language :: Python :: 3 :: Only
Classifier: Programming Language :: Python :: 3
Classifier: Programming Language :: Python :: 3.6
Classifier: Programming Language :: Python :: 3.7
Classifier: Programming Language :: Python :: 3.8
Classifier: Programming Language :: Python :: 3.9
Requires-Python: >=3.6
License-File: LICENSE
Requires-Dist: importlib-resources ; python_version < "3.7"
Provides-Extra: django
Requires-Dist: django (>=2.2) ; extra == 'django'
Provides-Extra: jinja
Requires-Dist: jinja2 (>=2.8) ; extra == 'jinja'
